doujinApi/__init__.py
doujinApi/api.py
doujinApi/book/__init__.py
doujinApi/book/methods.py
doujinApi/book/parser.py
doujinApi/book/request.py
doujinApi/book/response.py
doujinApi/config.py
doujinApi/item/__init__.py
doujinApi/item/constants.py
doujinApi/item/methods.py
doujinApi/item/parser.py
doujinApi/item/request.py
doujinApi/typings/__init__.py
doujinApi/typings/cast.py
doujinApi/typings/constants.py
doujinApi/typings/response_dataclass.py
doujinApi/typings/tag.py
doujinApi/utils/__init__.py
doujinApi/utils/exception.py
doujinApi/utils/parser.py
doujinApi/utils/session.py
LICENSE
README.md
doujinapi-0.1.0.dist-info/LICENSE
doujinapi-0.1.0.dist-info/WHEEL
doujinapi-0.1.0.dist-info/METADATA
doujinapi-0.1.0.dist-info/RECORD
