Metadata-Version: 2.1
Name: doujinapi
Version: 0.1.0
Summary: Doujinshi.org unofficial wrapper of official API
Home-page: https://github.com/Dosugamea/DoujinAPI2-py#readme
License: AGPLv3
Keywords: doujinshi,manga,search
Author: Dosugamea
Author-email: dsgamer777@gmail.com
Requires-Python: >=3.8,<4.0
Classifier: Development Status :: 3 - Alpha
Classifier: Intended Audience :: Developers
Classifier: License :: Other/Proprietary License
Classifier: Programming Language :: Python :: 3
Classifier: Programming Language :: Python :: 3.10
Classifier: Programming Language :: Python :: 3.8
Classifier: Programming Language :: Python :: 3.9
Classifier: Topic :: Utilities
Requires-Dist: dataclasses-json (>=0.5.7,<0.6.0)
Requires-Dist: httpx (>=0.22.0,<0.23.0)
Requires-Dist: python-dotenv[cli] (>=0.19.0,<0.20.0)
Requires-Dist: single-source (>=0.3.0,<0.4.0)
Project-URL: Repository, https://github.com/Dosugamea/DoujinAPI2-py
